README.md
setup.py
test/test.py
yundama/Logger.py
yundama/Yundama.py
yundama/__init__.py
yundama/fateadm_api.py
yundama.egg-info/PKG-INFO
yundama.egg-info/SOURCES.txt
yundama.egg-info/dependency_links.txt
yundama.egg-info/requires.txt
yundama.egg-info/top_level.txt