Metadata-Version: 2.1
Name: yundama
Version: 0.1.2
Summary: 使用 斐斐打码 对验证码进行打码
Home-page: https://github.com/twodogegg/yundama
Author: twodogegg
Author-email: 971270272@qq.com
License: MIT License
Keywords: dama 打码
Platform: any
